pyimagecuda_studio/__init__.py
pyimagecuda_studio/cli.py
pyimagecuda_studio/gui/config.py
pyimagecuda_studio/gui/export.py
pyimagecuda_studio/gui/main_window.py
pyimagecuda_studio/gui/qt_helpers.py
pyimagecuda_studio/gui/node_editor/__init__.py
pyimagecuda_studio/gui/node_editor/cable_widget.py
pyimagecuda_studio/gui/node_editor/node.py
pyimagecuda_studio/gui/node_editor/node_editor.py
pyimagecuda_studio/gui/node_editor/node_graph.py
pyimagecuda_studio/gui/preview/__init__.py
pyimagecuda_studio/gui/preview/gl_preview.py
pyimagecuda_studio/gui/preview/preview_dock.py
pyimagecuda_studio/gui/project/__init__.py
pyimagecuda_studio/gui/project/code_approval_dialog.py
pyimagecuda_studio/gui/project/project_operations.py
pyimagecuda_studio/gui/properties/__init__.py
pyimagecuda_studio/gui/properties/custom_properties.py
pyimagecuda_studio/gui/properties/global_variables_widget.py
pyimagecuda_studio/gui/properties/node_properties.py
pyimagecuda_studio/gui/properties/properties_factory.py
pyimagecuda_studio/icons/blend_node.svg
pyimagecuda_studio/icons/color_node.svg
pyimagecuda_studio/icons/eye_closed.svg
pyimagecuda_studio/icons/eye_open.svg
pyimagecuda_studio/icons/image_node.svg
pyimagecuda_studio/icons/mask_node.svg
pyimagecuda_studio/icons/others_node.svg
pyimagecuda_studio/icons/resize_node.svg
pyimagecuda_studio/icons/scale_node.svg
pyimagecuda_studio/icons/split_node.svg
pyimagecuda_studio/icons/text_node.svg
pyimagecuda_studio/nodes/__init__.py
pyimagecuda_studio/nodes/buffers.py
pyimagecuda_studio/nodes/constraints.py
pyimagecuda_studio/nodes/core.py
pyimagecuda_studio/nodes/global_variables.py
pyimagecuda_studio/nodes/headless.py
pyimagecuda_studio/nodes/node_factory.py
pyimagecuda_studio/nodes/node_generator.py
pyimagecuda_studio/nodes/node_in_out.py
pyimagecuda_studio/nodes/node_merge.py
pyimagecuda_studio/nodes/node_split.py
pyimagecuda_studio/nodes/serialization.py
pyimagecuda_studio/nodes/utils.py
pyimagecuda_studio/nodes/adjust/__init__.py
pyimagecuda_studio-0.1.7.dist-info/licenses/LICENSE
pyimagecuda_studio-0.1.7.dist-info/METADATA
pyimagecuda_studio-0.1.7.dist-info/WHEEL
pyimagecuda_studio-0.1.7.dist-info/entry_points.txt
pyimagecuda_studio-0.1.7.dist-info/top_level.txt
pyimagecuda_studio-0.1.7.dist-info/RECORD
