Metadata-Version: 2.4
Name: pyimagecuda-studio
Version: 0.1.7
Summary: Node-based image processing powered by CUDA - Design visually, execute programmatically
Author: Beltrán Offerrall Selma
License: MIT
Project-URL: Homepage, https://github.com/offerrall/pyimagecuda-studio
Keywords: cuda,image-processing,nodes,gui,batch-processing,headless,pipeline
Classifier: Development Status :: 4 - Beta
Classifier: Intended Audience :: Developers
Classifier: Intended Audience :: Science/Research
Classifier: License :: OSI Approved :: MIT License
Classifier: Operating System :: OS Independent
Classifier: Programming Language :: Python :: 3
Classifier: Programming Language :: Python :: 3.10
Classifier: Programming Language :: Python :: 3.11
Classifier: Programming Language :: Python :: 3.12
Classifier: Programming Language :: Python :: 3.13
Classifier: Topic :: Multimedia :: Graphics
Classifier: Topic :: Scientific/Engineering :: Image Processing
Requires-Python: <3.14,>=3.10
License-File: LICENSE
Requires-Dist: PySide6>=6.10.0
Requires-Dist: pyimagecuda>=0.1.4
Requires-Dist: PyOpenGL>=3.1.10
Requires-Dist: PyOpenGL_accelerate>=3.1.10
Dynamic: license-file
